mycalc2/__init__.py
mycalc2/calculator.py
mycalc2/models/__init__.py
mycalc2/models/model_calculator.py
mycalc2/utils/__init__.py
mycalc2/utils/extra/__init__.py
mycalc2/utils/extra/arithematic.py
mycalc2/utils/numerical_utils.py
mycalc2/utils/sample.py
mycalc2-0.2.2.dist-info/WHEEL
mycalc2-0.2.2.dist-info/METADATA
mycalc2-0.2.2.dist-info/RECORD
